Workbook

Sheet 01_今日输入
A1: V2.8.6 今日输入
A2: 蓝字为可编辑输入；黑字为公式；本表只做纪律提醒，不构成自动交易指令。
A4: 字段 | B4: 输入值 | C4: 说明
A5: 日期 | B5: 46203 | C5: 交易日
A6: 总量锚 | B6: 绿 | C6: 绿/黄/红
A7: 成长锚 | B7: 绿 | C7: 绿/黄/红
A8: 情绪温度 | B8: 4 | C8: 0-10，越高越热
A9: 证券账户可用资金 | B9: 222000 | C9: 用于计算单次买入上限
A10: 全资产目标金额 | B10: 4783000 | C10: 第一年配置表口径
A11: 现金安全垫是否达标 | B11: 是 | C11: 是/否
A12: 今日最多买入方向 | B12: 1 | C12: 纪律上限
A13: 今日最多减仓方向 | B13: 2 | C13: 风控优先

Sheet 02_评分规则
A1: ETF质量与买点评分规则
A2: 蓝字为可编辑输入；黑字为公式；本表只做纪律提醒，不构成自动交易指令。
A5: 模块 | B5: 权重 | C5: 评分说明 | D5: 通过线 | E5: 一票否决
A6: 主线匹配 | B6: 2 | C6: 未来三年利润分配中心；政策、产业、盈利至少三项成立 | D6: 1.5 | E6: 纯题材无盈利验证
A7: 资金语言 | B7: 2 | C7: 成交额、ETF份额、相对强度、龙头承接 | D7: 1.5 | E7: 连续放量下跌/净赎回恶化
A8: 资产质量 | B8: 2 | C8: 指数成分、景气、兑现、替代难度 | D8: 1.5 | E8: 质量评分低于8
A9: 估值情绪 | B9: 2 | C9: 估值分位、拥挤度、媒体热度、涨幅透支 | D9: 1 | E9: 情绪温度≥7
A10: 技术买点 | B10: 2 | C10: 回踩、突破、止跌三类买点确认质量 | D10: 1.5 | E10: 无确认，只因年度缺口补仓

Sheet 03_阶段推进
A1: 阶段达标后再加仓检查
A2: 蓝字为可编辑输入；黑字为公式；本表只做纪律提醒，不构成自动交易指令。
A4: Code | B4: Name | C4: 年度目标占比 | D4: 当前全资产占比 | E4: 当前阶段 | F4: 阶段目标下限 | G4: 阶段目标上限 | H4: 质量评分 | I4: 买点类型 | J4: 阶段验证 | K4: 年度缺口 | L4: 阶段占用率 | M4: 下一档结论 | N4: 建议单次上限 | O4: 阻断原因/备注
A5: 159516 | B5: 半导体设备ETF | C5: 0.1 | D5: 0.0131 | E5: 观察仓 | F5: 0 | G5: 0.2 | H5: 8.8 | I5: 回踩确认 | J5: 是 | K5: =MAX(0,C5-D5) | L5: =IF(C5=0,0,D5/C5) | M5: =IF(OR('01_今日输入'!$B$6="红",'01_今日输入'!$B$7="红",'01_今日输入'!$B$8>=7,H5<8),"暂停/降级",IF(AND(J5="是",K5>0,L5>=G5,'01_今日输入'!$B$8<=4),"允许下一档",IF(AND(K5>0,H5>=8,'01_今日输入'!$B$8<=5),"小额防踏空","等待"))) | N5: =IF(M5="允许下一档",MIN('01_今日输入'!$B$9*0.15,'01_今日输入'!$B$10*0.015),IF(M5="小额防踏空",MIN('01_今日输入'!$B$9*0.08,'01_今日输入'!$B$10*0.005),0))
A6: 562500 | B6: 机器人ETF | C6: 0.08 | D6: 0.0288 | E6: 验证仓 | F6: 0.2 | G6: 0.4 | H6: 8.2 | I6: 持有不加 | J6: 否 | K6: =MAX(0,C6-D6) | L6: =IF(C6=0,0,D6/C6) | M6: =IF(OR('01_今日输入'!$B$6="红",'01_今日输入'!$B$7="红",'01_今日输入'!$B$8>=7,H6<8),"暂停/降级",IF(AND(J6="是",K6>0,L6>=G6,'01_今日输入'!$B$8<=4),"允许下一档",IF(AND(K6>0,H6>=8,'01_今日输入'!$B$8<=5),"小额防踏空","等待"))) | N6: =IF(M6="允许下一档",MIN('01_今日输入'!$B$9*0.15,'01_今日输入'!$B$10*0.015),IF(M6="小额防踏空",MIN('01_今日输入'!$B$9*0.08,'01_今日输入'!$B$10*0.005),0)) | O6: 当前不追高
A7: 159381 | B7: 创业板人工智能ETF | C7: 0.07 | D7: 0.0047 | E7: 观察仓 | F7: 0 | G7: 0.2 | H7: 8.5 | I7: 止跌确认 | J7: 是 | K7: =MAX(0,C7-D7) | L7: =IF(C7=0,0,D7/C7) | M7: =IF(OR('01_今日输入'!$B$6="红",'01_今日输入'!$B$7="红",'01_今日输入'!$B$8>=7,H7<8),"暂停/降级",IF(AND(J7="是",K7>0,L7>=G7,'01_今日输入'!$B$8<=4),"允许下一档",IF(AND(K7>0,H7>=8,'01_今日输入'!$B$8<=5),"小额防踏空","等待"))) | N7: =IF(M7="允许下一档",MIN('01_今日输入'!$B$9*0.15,'01_今日输入'!$B$10*0.015),IF(M7="小额防踏空",MIN('01_今日输入'!$B$9*0.08,'01_今日输入'!$B$10*0.005),0))
A8: 588700 | B8: 创新药ETF | C8: 0.03 | D8: 0 | E8: 观察池 | F8: 0 | G8: 0.2 | H8: 7.8 | I8: 等待 | J8: 否 | K8: =MAX(0,C8-D8) | L8: =IF(C8=0,0,D8/C8) | M8: =IF(OR('01_今日输入'!$B$6="红",'01_今日输入'!$B$7="红",'01_今日输入'!$B$8>=7,H8<8),"暂停/降级",IF(AND(J8="是",K8>0,L8>=G8,'01_今日输入'!$B$8<=4),"允许下一档",IF(AND(K8>0,H8>=8,'01_今日输入'!$B$8<=5),"小额防踏空","等待"))) | N8: =IF(M8="允许下一档",MIN('01_今日输入'!$B$9*0.15,'01_今日输入'!$B$10*0.015),IF(M8="小额防踏空",MIN('01_今日输入'!$B$9*0.08,'01_今日输入'!$B$10*0.005),0)) | O8: 需二次确认
A9: 512890 | B9: 红利低波ETF | C9: 0.05 | D9: 0.0089 | E9: 防守仓 | F9: 0 | G9: 0.4 | H9: 7.5 | I9: 慢建 | J9: 是 | K9: =MAX(0,C9-D9) | L9: =IF(C9=0,0,D9/C9) | M9: =IF(OR('01_今日输入'!$B$6="红",'01_今日输入'!$B$7="红",'01_今日输入'!$B$8>=7,H9<8),"暂停/降级",IF(AND(J9="是",K9>0,L9>=G9,'01_今日输入'!$B$8<=4),"允许下一档",IF(AND(K9>0,H9>=8,'01_今日输入'!$B$8<=5),"小额防踏空","等待"))) | N9: =IF(M9="允许下一档",MIN('01_今日输入'!$B$9*0.15,'01_今日输入'!$B$10*0.015),IF(M9="小额防踏空",MIN('01_今日输入'!$B$9*0.08,'01_今日输入'!$B$10*0.005),0)) | O9: 不当现金安全垫

Sheet 04_ETF执行计划
A1: ETF执行计划
A2: 蓝字为可编辑输入；黑字为公式；本表只做纪律提醒，不构成自动交易指令。
A4: 优先级 | B4: Code | C4: Name | D4: 定位 | E4: 买点优先级 | F4: 第一笔 | G4: 第二笔 | H4: 第三笔 | I4: 失效条件 | J4: 下一复核
A5: 1 | B5: 159516 | C5: 半导体设备ETF | D5: 第一核心候选 | E5: 回踩确认>止跌确认>突破试探 | F5: 观察/验证仓 | G5: 核心仓 | H5: 目标仓 | I5: 跌破确认位且无修复 | J5: T+3/T+10/月末
A6: 2 | B6: 159381 | C6: 创业板人工智能ETF | D6: AI硬件增强仓 | E6: 回踩确认优先 | F6: 观察仓 | G6: 验证仓 | H6: 核心仓 | I6: 主线相对强度转弱 | J6: T+3/T+10/月末
A7: 3 | B7: 562500 | C7: 机器人ETF | D7: 核心持有 | E7: 止跌三步确认 | F7: 持有不加 | G7: 验证后再议 | H7: 目标仓 | I7: 强势追高或放量下跌 | J7: 月末
A8: 4 | B8: 588700 | C8: 创新药ETF | D8: 核心观察 | E8: 二次确认 | F8: 观察仓 | G8: 验证仓 | H8: 核心仓 | I8: 政策/临床/资金任一证伪 | J8: 周度
A9: 5 | B9: 512890 | C9: 红利低波ETF | D9: 低波权益 | E9: 慢建 | F9: 小额慢建 | G9: 月度再平衡 | H9: 目标仓 | I9: 不替代现金安全垫 | J9: 月末

Sheet 05_持仓复核
A1: 持仓风险与退出复核
A2: 蓝字为可编辑输入；黑字为公式；本表只做纪律提醒，不构成自动交易指令。
A4: 风险级别 | B4: Code | C4: Name | D4: 当前定位 | E4: 触发原因 | F4: 动作建议 | G4: 是否允许加仓 | H4: 复核周期
A5: 红 | B5: 002594 | C5: 比亚迪 | D5: 2030战略观察仓 | E5: 超过普通非核心新增资格 | F5: 不追涨，按战略观察仓复核 | G5: 否 | H5: 月度
A6: 红 | B6: 516630 | C6: 云计算ETF | D6: 泛AI降级观察 | E6: 非核心且目标为0 | F6: 反弹复审，不恢复加仓资格 | G6: 否 | H6: 周度
A7: 黄 | B7: 562550 | C7: 绿电ETF | D7: 非核心保留仓 | E7: 遗留仓 | F7: 暂不新增，等待退出窗口 | G7: 否 | H7: 月度
A8: 黄 | B8: 688083 | C8: 中望软件 | D8: 遗留个股 | E8: 质量评分不足 | F8: 只做退出复审 | G8: 否 | H8: 周度
A9: 灰 | B9: 562500 | C9: 机器人ETF | D9: 核心持有 | E9: 未触发减仓 | F9: 持有不加，等待阶段验证 | G9: 条件满足后 | H9: 月度

Sheet 06_复盘日志
A1: 交易复盘日志
A2: 蓝字为可编辑输入；黑字为公式；本表只做纪律提醒，不构成自动交易指令。
A4: 日期 | B4: Code | C4: Name | D4: 动作 | E4: 金额 | F4: 买点类型 | G4: 执行依据 | H4: 确认位/失效位 | I4: T+3结果 | J4: T+10结果 | K4: 月末结论 | L4: 改进项

Sheet 07_Checks
A1: 检查项
A2: 蓝字为可编辑输入；黑字为公式；本表只做纪律提醒，不构成自动交易指令。
A4: 检查项 | B4: 结果 | C4: 说明
A5: 公式错误 | B5: =IF(COUNTIF('03_阶段推进'!K5:N100,"#VALUE!")+COUNTIF('03_阶段推进'!K5:N100,"#REF!")=0,"OK","检查公式") | C5: 主要公式区域不应出现错误。
A6: 现金安全垫 | B6: =IF('01_今日输入'!B11="是","OK","暂停新增") | C6: 现金安全垫未达标则不新增。
A7: 情绪温度 | B7: =IF('01_今日输入'!B8<7,"OK","暂停新增") | C7: 情绪温度≥7 时暂停新增。
A8: 今日买入方向上限 | B8: =IF('01_今日输入'!B12<=1,"OK","调整为最多1个") | C8: 避免一天同时追多个方向。
